hadoop_test_cluster/__init__.py
hadoop_test_cluster/cli.py
hadoop_test_cluster/docker-compose.yaml
hadoop_test_cluster/krb5.conf
hadoop_test_cluster-0.1.0.dist-info/METADATA
hadoop_test_cluster-0.1.0.dist-info/RECORD
hadoop_test_cluster-0.1.0.dist-info/WHEEL
hadoop_test_cluster-0.1.0.dist-info/entry_points.txt
hadoop_test_cluster-0.1.0.dist-info/top_level.txt
