Metadata-Version: 2.1
Name: hadoop-test-cluster
Version: 0.1.0
Summary: A CLI for managing hadoop clusters for testing
Home-page: https://github.com/jcrist/hadoop-test-cluster
Author: Jim Crist
Author-email: jiminy.crist@gmail.com
License: BSD
Platform: UNKNOWN
